chat/README.md
chat/chat.py
chat/hi.py
chat/requirements.txt
chat/run.sh
chat/system.py
chat/tdz.html
examples/agent-ex-1-17.py
examples/agent-ex-2-17.py
examples/agent-ex-3-17.py
examples/api-ex-1-12.py
examples/api-ex-2-12.py
examples/api-ex-3-12.py
examples/api-ex-4-12.py
examples/api-ex-5-12.py
examples/chunking-ex-1-2.py
examples/chunking-ex-2-2.py
examples/chunking-ex-3-2.py
examples/chunking-ex-4-2.py
examples/chunking-ex-5-2.py
examples/cli-ex-2-14.py
examples/cli-ex-3-14.py
examples/cli-ex-4-14.py
examples/cli-ex-5-14.py
examples/error-ex-1-4.py
examples/error-ex-2-4.py
examples/error-ex-3-4.py
examples/error-ex-4-4.py
examples/error-ex-5-4.py
examples/lib-ex-2-7.py
examples/lib-ex-4-7.py
examples/lib-ex-5-7.py
examples/memory-ex-1-6.py
examples/memory-ex-2-6.py
examples/memory-ex-3-6.py
examples/memory-ex-4-6.py
examples/memory-ex-5-6.py
examples/models-ex-1-5.py
examples/models-ex-2-5.py
examples/models-ex-3-5.py
examples/models-ex-4-5.py
examples/models-ex-5-5.py
examples/random-ex-1.py
examples/random-ex-2.py
examples/random-ex-3.py
examples/server-ex-2-3.py
examples/server-ex-3-3.py
examples/server-ex-4-3.py
examples/server-ex-5-3.py
examples/storage-ex-2-16.py
examples/storage-ex-4-16.py
examples/storage-ex-5-16.py
examples/summary-ex-1-13.py
examples/summary-ex-2-13.py
examples/summary-ex-3-13.py
examples/summary-ex-4-13.py
examples/summary-ex-5-13.py
examples/tags-ex-1-1.py
examples/tags-ex-2-1.py
examples/tags-ex-3-1.py
examples/tags-ex-4-1.py
examples/tags-ex-5-1.py
examples/tdz_dne-ex-1-11.py
examples/tdz_dne-ex-2-11.py
examples/tdz_dne-ex-3-11.py
examples/tdz_dne-ex-4-11.py
examples/tdz_dne-ex-5-11.py
examples/tdz_tls-ex-1-15.py
examples/tdz_tls-ex-2-15.py
examples/tdz_tls-ex-3-15.py
examples/tdz_tls-ex-4-15.py
examples/tdz_tls-ex-5-15.py
examples/todozi-ex-1-8.py
examples/todozi-ex-2-8.py
examples/todozi-ex-3-8.py
examples/todozi-ex-4-8.py
examples/todozi-ex-5-8.py
examples/types-ex-1-10.py
examples/types-ex-2-10.py
examples/types-ex-3-10.py
todozi-0.1.8.dist-info/METADATA
todozi-0.1.8.dist-info/WHEEL
todozi-0.1.8.dist-info/entry_points.txt
todozi-0.1.8.dist-info/top_level.txt
todozi-0.1.8.dist-info/RECORD
