Metadata-Version: 2.4
Name: todozi
Version: 0.1.8
Summary: AI/Human task management system with file-based storage
Home-page: https://github.com/cyber-boost/todozi
Author: CyberBoost
License: MIT
Project-URL: Homepage, https://todozi.com
Project-URL: Repository, https://github.com/cyber-boost/todozi
Project-URL: Documentation, https://todozi.com
Project-URL: Bug Tracker, https://github.com/cyber-boost/todozi/issues
Classifier: Development Status :: 3 - Alpha
Classifier: Intended Audience :: Developers
Classifier: Programming Language :: Python :: 3
Classifier: Programming Language :: Python :: 3.8
Classifier: Programming Language :: Python :: 3.9
Classifier: Programming Language :: Python :: 3.10
Classifier: Programming Language :: Python :: 3.11
Classifier: Programming Language :: Python :: 3.12
Classifier: Topic :: Software Development :: Libraries :: Python Modules
Classifier: Topic :: System :: Shells
Classifier: Topic :: Utilities
Classifier: Topic :: Scientific/Engineering :: Artificial Intelligence
Requires-Python: >=3.8
Requires-Dist: fastapi>=0.111.0
Requires-Dist: uvicorn[standard]>=0.30.0
Requires-Dist: sqlmodel>=0.0.16
Requires-Dist: pydantic>=2.6.0
Requires-Dist: pydantic-settings>=2.3.0
Requires-Dist: python-multipart>=0.0.9
Requires-Dist: torch>=2.0.0
Requires-Dist: transformers>=4.36.0
Requires-Dist: sentence-transformers
Requires-Dist: tokenizers
Requires-Dist: trl>=0.7.0
Requires-Dist: datasets>=2.14.0
Requires-Dist: gradio<5.0.0,>=4.0.0
Requires-Dist: accelerate>=0.24.0
Requires-Dist: safetensors>=0.4.0
Requires-Dist: tqdm
Requires-Dist: aiohttp
Requires-Dist: aiofiles
Requires-Dist: structlog
Requires-Dist: textual>=0.19.0
Requires-Dist: rich>=13.0.0
Requires-Dist: ollama>=0.2.0
Requires-Dist: requests>=2.31.0
Requires-Dist: watchdog
Dynamic: home-page
Dynamic: requires-python
